./.gitignore
./LICENSE
./PKG-INFO
./README.md
./__init__.py
./cli.py
./pyproject.toml
./server.py
./econometrics/README.md
./econometrics/__init__.py
./econometrics/未开发大类优先级分析.md
./econometrics/advanced_methods/modern_computing_machine_learning/__init__.py
./econometrics/advanced_methods/modern_computing_machine_learning/causal_forest.py
./econometrics/advanced_methods/modern_computing_machine_learning/double_ml.py
./econometrics/advanced_methods/modern_computing_machine_learning/gradient_boosting.py
./econometrics/advanced_methods/modern_computing_machine_learning/hierarchical_clustering.py
./econometrics/advanced_methods/modern_computing_machine_learning/kmeans_clustering.py
./econometrics/advanced_methods/modern_computing_machine_learning/neural_network.py
./econometrics/advanced_methods/modern_computing_machine_learning/random_forest.py
./econometrics/advanced_methods/modern_computing_machine_learning/support_vector_machine.py
./econometrics/advanced_methods/modern_computing_machine_learning/test_all_modules.py
./econometrics/advanced_methods/modern_computing_machine_learning/test_report.md
./econometrics/basic_parametric_estimation/__init__.py
./econometrics/basic_parametric_estimation/gmm/__init__.py
./econometrics/basic_parametric_estimation/gmm/gmm_model.py
./econometrics/basic_parametric_estimation/mle/__init__.py
./econometrics/basic_parametric_estimation/mle/mle_model.py
./econometrics/basic_parametric_estimation/ols/__init__.py
./econometrics/basic_parametric_estimation/ols/ols_model.py
./econometrics/causal_inference/__init__.py
./econometrics/causal_inference/causal_identification_strategy/__init__.py
./econometrics/causal_inference/causal_identification_strategy/control_function.py
./econometrics/causal_inference/causal_identification_strategy/difference_in_differences.py
./econometrics/causal_inference/causal_identification_strategy/event_study.py
./econometrics/causal_inference/causal_identification_strategy/first_difference.py
aigroup_econ_mcp-2.0.7.dist-info/METADATA
aigroup_econ_mcp-2.0.7.dist-info/WHEEL
aigroup_econ_mcp-2.0.7.dist-info/entry_points.txt
aigroup_econ_mcp-2.0.7.dist-info/licenses/LICENSE
aigroup_econ_mcp-2.0.7.dist-info/RECORD
