Metadata-Version: 2.4
Name: aigroup_econ_mcp
Version: 2.0.7
Summary: 专业计量经济学MCP工具 - 支持CSV/JSON/TXT/Excel格式，让大模型更智能地进行数据分析
Project-URL: Homepage, https://github.com/jackdark425/aigroup-econ-mcp
Project-URL: Repository, https://github.com/jackdark425/aigroup-econ-mcp.git
Project-URL: Issues, https://github.com/ajackdark425/aigroup-econ-mcp/issues
Author-email: AIGroup <jackdark425@gmail.com>
License-File: LICENSE
Keywords: data-analysis,econometrics,economics,mcp,panel-data,regression,statistics,time-series
Classifier: Development Status :: 5 - Production/Stable
Classifier: Intended Audience :: Developers
Classifier: License :: OSI Approved :: MIT License
Classifier: Programming Language :: Python :: 3
Classifier: Programming Language :: Python :: 3.8
Classifier: Programming Language :: Python :: 3.9
Classifier: Programming Language :: Python :: 3.10
Classifier: Programming Language :: Python :: 3.11
Classifier: Programming Language :: Python :: 3.12
Classifier: Topic :: Scientific/Engineering :: Information Analysis
Classifier: Topic :: Software Development :: Libraries :: Python Modules
Requires-Python: >=3.10
Requires-Dist: arch>=6.0.0
Requires-Dist: click>=8.0.0
Requires-Dist: esda>=2.4.0
Requires-Dist: joblib>=1.2.0
Requires-Dist: libpysal>=4.7.0
Requires-Dist: lifelines>=0.27.0
Requires-Dist: linearmodels>=7.0
Requires-Dist: matplotlib>=3.5.0
Requires-Dist: mcp>=1.0.0
Requires-Dist: numpy>=1.21.0
Requires-Dist: openpyxl>=3.0.0
Requires-Dist: pandas>=1.5.0
Requires-Dist: psutil>=5.9.0
Requires-Dist: pydantic>=2.0.0
Requires-Dist: pyyaml>=6.0
Requires-Dist: scikit-learn>=1.0.0
Requires-Dist: scipy>=1.7.0
Requires-Dist: spreg>=1.4.0
Requires-Dist: statsmodels>=0.13.0
Requires-Dist: twine>=6.2.0
Requires-Dist: uvicorn>=0.20.0
Requires-Dist: xgboost>=1.7.0
